unicef_locations/.DS_Store
unicef_locations/__init__.py
unicef_locations/admin.py
unicef_locations/apps.py
unicef_locations/auth.py
unicef_locations/cache.py
unicef_locations/config.py
unicef_locations/exceptions.py
unicef_locations/forms.py
unicef_locations/libs.py
unicef_locations/models.py
unicef_locations/serializers.py
unicef_locations/synchronizers.py
unicef_locations/tasks.py
unicef_locations/urls.py
unicef_locations/utils.py
unicef_locations/views.py
unicef_locations/migrations/0001_initial.py
unicef_locations/migrations/__init__.py
unicef_locations/templates/admin/location_remap.html
unicef_locations/tests/__init__.py
unicef_locations/tests/factories.py
unicef_locations-4.2.dist-info/LICENSE
unicef_locations-4.2.dist-info/METADATA
unicef_locations-4.2.dist-info/WHEEL
unicef_locations-4.2.dist-info/top_level.txt
unicef_locations-4.2.dist-info/RECORD
